gkit/__init__.py
gkit/cli.py
gkit/functions.py
gkit/io.py
gkit/math.py
gkit/core/__init__.py
gkit/core/functions.py
gkit/core/raster.py
gkit-0.6.5.dist-info/LICENSE
gkit-0.6.5.dist-info/METADATA
gkit-0.6.5.dist-info/WHEEL
gkit-0.6.5.dist-info/entry_points.txt
gkit-0.6.5.dist-info/top_level.txt
gkit-0.6.5.dist-info/RECORD
