Metadata-Version: 2.1
Name: gkit
Version: 0.6.5
Summary: Gkit is a suit of utilites for processing geo-dataset.
Home-page: https://github.com/TitorX/gkit
Author: titor
Author-email: titor.sun@gmail.com
License: UNKNOWN
Platform: UNKNOWN
Requires-Dist: numpy
Requires-Dist: fire
Requires-Dist: matplotlib
